{
  "name": "Cichlidé nain à deux bandes",
  "scientificName": "Apistogramma bitaeniata",
  "slug": "apistogramma-bitaeniata",
  "biotope": "Eau douce — Amazonie",
  "difficulty": 1,
  "tempMin": 23,
  "tempMax": 27,
  "phMin": 5,
  "phMax": 7,
  "ghMin": 1,
  "ghMax": 10,
  "khMin": null,
  "khMax": null,
  "minVolumeL": 100,
  "minLengthCm": 8,
  "behavior": "Population: 2 minimum. Zone: Inférieure. Ratio M/F: 1 / 1",
  "compatibility": "Zone inférieure.",
  "diet": "Non renseigné",
  "breeding": "Ovipare",
  "notes": null,
  "images": [
    "https://www.b-aqua.com/photos/1/419.jpg"
  ],
  "gallery": [],
  "tags": [
    "eau-douce",
    "facile"
  ]
}