{
  "name": "Canthigaster valentini",
  "scientificName": "Canthigaster valentini",
  "slug": "canthigaster-valentini",
  "biotope": "Eau de mer",
  "difficulty": 1,
  "tempMin": 23,
  "tempMax": 24,
  "phMin": 7.6,
  "phMax": 8.5,
  "ghMin": null,
  "ghMax": null,
  "khMin": null,
  "khMax": null,
  "minVolumeL": null,
  "minLengthCm": 10,
  "behavior": "Actif, nage parmi les coraux et roches du récif.",
  "compatibility": "Compatible avec les poissons récifaux de tempérament similaire.",
  "diet": "Omnivore marin : mysis, artémias, nourriture congelée marine, paillettes marines.",
  "breeding": "Ovipare. Reproduction rare en captivité.",
  "notes": "Bac récifal avec paramètres stables. Qualité de l'eau excellente requise.",
  "images": [
    "https://upload.wikimedia.org/wikipedia/commons/thumb/b/b0/Canthigaster_valentini_1.jpg/960px-Canthigaster_valentini_1.jpg"
  ],
  "gallery": [],
  "tags": [
    "marin",
    "facile"
  ]
}