{
  "name": "Labre aux yeux rouges",
  "scientificName": "Cirrhilabrus solorensis",
  "slug": "cirrhilabrus-solorensis",
  "biotope": "Eau de mer",
  "difficulty": 1,
  "tempMin": 24,
  "tempMax": 28,
  "phMin": 8,
  "phMax": 8.4,
  "ghMin": 8,
  "ghMax": 12,
  "khMin": 7,
  "khMax": 12,
  "minVolumeL": 300,
  "minLengthCm": 8,
  "behavior": "Paisible, actif, nage en pleine eau. Les mâles paradent avec des couleurs spectaculaires.",
  "compatibility": "Excellent en récifal, reef-safe. Compatible avec la plupart des poissons.",
  "diet": "Planctivore/carnivore : mysis, artémias enrichies, cyclopes, nourriture fine congelée.",
  "breeding": "Ovipare. Reproduction très rare en captivité. Ponte pélagique au crépuscule.",
  "notes": "Labres magnifiques. Bac couvert (sauteur). Nourrir 2-3 fois par jour avec du vivant/congelé.",
  "images": [
    "https://www.b-aqua.com/photos/1/1133.jpg"
  ],
  "gallery": [],
  "tags": [
    "marin",
    "facile"
  ]
}