{
  "name": "Cirrhilabrus exquisitus",
  "scientificName": "Cirrhilabrus exquisitus",
  "slug": "cirrhilabrus-exquisitus",
  "biotope": "Eau de mer",
  "difficulty": 1,
  "tempMin": 26,
  "tempMax": 28,
  "phMin": 7,
  "phMax": 8,
  "ghMin": null,
  "ghMax": null,
  "khMin": null,
  "khMax": null,
  "minVolumeL": null,
  "minLengthCm": 12,
  "behavior": "Zone: Inférieure, Centrale",
  "compatibility": "Zone inférieure, centrale.",
  "diet": "Planctivore/carnivore : mysis, artémias enrichies, cyclopes, nourriture fine congelée.",
  "breeding": "Ovipare. Reproduction très rare en captivité. Hermaphrodisme protogyne.",
  "notes": "Labres magnifiques. Bac couvert (sauteur). Nourrir 2-3 fois par jour avec du vivant/congelé.",
  "images": [],
  "gallery": [],
  "tags": [
    "marin",
    "facile"
  ]
}