{
  "name": "Etheostoma pottsii",
  "scientificName": "Etheostoma pottsii",
  "slug": "etheostoma-pottsii",
  "biotope": "Eau douce",
  "difficulty": 1,
  "tempMin": null,
  "tempMax": null,
  "phMin": null,
  "phMax": null,
  "ghMin": null,
  "ghMax": null,
  "khMin": null,
  "khMax": null,
  "minVolumeL": null,
  "minLengthCm": 5.5,
  "behavior": "Zone: Fond",
  "compatibility": "Zone fond.",
  "diet": "Non renseigné",
  "breeding": null,
  "notes": null,
  "images": [
    "https://upload.wikimedia.org/wikipedia/commons/thumb/9/98/FMIB_40096_Etheostoma_micropterus_Gilbert_Chihuahua%2C_Mexico.jpeg/960px-FMIB_40096_Etheostoma_micropterus_Gilbert_Chihuahua%2C_Mexico.jpeg"
  ],
  "gallery": [],
  "tags": [
    "eau-douce",
    "facile"
  ]
}