{
  "name": "Fundulopanchax fallax",
  "scientificName": "Fundulopanchax fallax",
  "slug": "fundulopanchax-fallax",
  "biotope": "Eau douce — Afrique",
  "difficulty": 1,
  "tempMin": 22,
  "tempMax": 26,
  "phMin": 5,
  "phMax": 7,
  "ghMin": 0,
  "ghMax": 12,
  "khMin": null,
  "khMax": null,
  "minVolumeL": null,
  "minLengthCm": 9,
  "behavior": "Population: 1 minimum (3 recommandé). Zone: Inférieure, Centrale. Ratio M/F: 1 / 2",
  "compatibility": "Compatible avec des espèces calmes de taille similaire. 1 mâle pour 2-3 femelles.",
  "diet": "Micro-prédateur : artémias, daphnies, vers grindal, moustiques, nourriture vivante préférée.",
  "breeding": "Ovipare, pondeur en mousse ou tourbe. Incubation des œufs variable selon l'espèce (2-6 semaines).",
  "notes": "Eau douce et acide. Bac sombre avec plantes flottantes. Couvercle obligatoire (sauteur).",
  "images": [
    "https://www.b-aqua.com/photos/1/1641.jpg"
  ],
  "gallery": [],
  "tags": [
    "eau-douce",
    "facile"
  ]
}