{
  "name": "Gastromyzon crenastus",
  "scientificName": "Gastromyzon crenastus",
  "slug": "gastromyzon-crenastus",
  "biotope": "Eau douce — Asie",
  "difficulty": 1,
  "tempMin": 20,
  "tempMax": 24,
  "phMin": 6.5,
  "phMax": 8,
  "ghMin": 3,
  "ghMax": 12,
  "khMin": 2,
  "khMax": 8,
  "minVolumeL": 80,
  "minLengthCm": 3,
  "behavior": "Paisible, vit fixé aux roches. Se déplace en se collant aux surfaces. Grégaire, préfère un groupe.",
  "compatibility": "Compatible avec les poissons de rivière rapide. Éviter les espèces de fond territoriales.",
  "diet": "Herbivore/périphyton : algues, biofilm, spiruline, courgettes blanchies. Courant fort nécessaire.",
  "breeding": "Ovipare. Reproduction possible en aquarium avec fort courant et eau fraîche bien oxygénée.",
  "notes": "voir G.scitulus.",
  "images": [
    "https://www.b-aqua.com/photos/1/1673.jpg"
  ],
  "gallery": [],
  "tags": [
    "eau-douce",
    "nano",
    "facile"
  ]
}