{
  "name": "Mormyrus Rume",
  "scientificName": "Mormyrus Rume",
  "slug": "mormyrus-rume",
  "biotope": "Eau douce — Afrique",
  "difficulty": 1,
  "tempMin": null,
  "tempMax": null,
  "phMin": null,
  "phMax": null,
  "ghMin": null,
  "ghMax": null,
  "khMin": null,
  "khMax": null,
  "minVolumeL": null,
  "minLengthCm": 80,
  "behavior": "Territorial, comportement social marqué. Hiérarchie intra-spécifique chez les cichlidés.",
  "compatibility": "Compatible avec des espèces africaines de biotope et tempérament similaires. Prévoir un espace suffisant.",
  "diet": "Omnivore : paillettes pour cichlidés, artémias, mysis, spiruline, nourriture congelée.",
  "breeding": "Généralement incubateur buccal. Soins parentaux développés.",
  "notes": "Eau dure et alcaline. Décor rocheux avec de nombreux territoires.",
  "images": [
    "https://upload.wikimedia.org/wikipedia/commons/thumb/e/e9/Mormyrus_rume.jpg/960px-Mormyrus_rume.jpg"
  ],
  "gallery": [],
  "tags": [
    "eau-douce",
    "omnivore",
    "grand",
    "facile"
  ]
}