{
  "name": "Nannostomus anduzei",
  "scientificName": "Nannostomus anduzei",
  "slug": "nannostomus-anduzei",
  "biotope": "Eau douce",
  "difficulty": 1,
  "tempMin": 24,
  "tempMax": 28,
  "phMin": 5,
  "phMax": 7,
  "ghMin": 0,
  "ghMax": 10,
  "khMin": null,
  "khMax": null,
  "minVolumeL": null,
  "minLengthCm": 1.8,
  "behavior": "Zone: Centrale, Supérieure",
  "compatibility": "Zone centrale, supérieure.",
  "diet": "Non renseigné",
  "breeding": null,
  "notes": null,
  "images": [],
  "gallery": [],
  "tags": [
    "eau-douce",
    "nano",
    "facile"
  ]
}