{
  "name": "Nemacheilus oxianus",
  "scientificName": "Nemacheilus oxianus",
  "slug": "nemacheilus-oxianus",
  "biotope": "Eau douce — Asie",
  "difficulty": 1,
  "tempMin": 4,
  "tempMax": 22,
  "phMin": 6,
  "phMax": 8,
  "ghMin": 2,
  "ghMax": 30,
  "khMin": null,
  "khMax": null,
  "minVolumeL": null,
  "minLengthCm": 7,
  "behavior": "Population: 6 minimum (12 recommandé). Zone: Inférieure. Ratio M/F: 1 / 1",
  "compatibility": "Compatible en bac communautaire asiatique avec des espèces paisibles de taille similaire.",
  "diet": "Omnivore : paillettes fines, artémias, daphnies, nourriture congelée fine.",
  "breeding": "Ovipare. Reproduction variable selon l'espèce.",
  "notes": "Bac planté avec espace de nage. Eau douce et légèrement acide.",
  "images": [],
  "gallery": [],
  "tags": [
    "eau-douce",
    "facile"
  ]
}