{
  "name": "Poisson Riz de Java",
  "scientificName": "Oryzias javanicus",
  "slug": "oryzias-javanicus",
  "biotope": "Eau saumâtre",
  "difficulty": 1,
  "tempMin": 22,
  "tempMax": 25,
  "phMin": 7.5,
  "phMax": 8.5,
  "ghMin": null,
  "ghMax": null,
  "khMin": null,
  "khMax": null,
  "minVolumeL": null,
  "minLengthCm": 4,
  "behavior": "Paisible, grégaire, vit en banc de 6 minimum. Nage en pleine eau.",
  "compatibility": "Excellent en communautaire avec des espèces paisibles.",
  "diet": "Omnivore : micro-paillettes, artémias nauplies, cyclopes, daphnies, nourriture fine.",
  "breeding": "Ovipare, disperseur d'œufs dans la végétation ou la mousse.",
  "notes": "Bac planté avec espace de nage. Eau douce et légèrement acide.",
  "images": [
    "https://upload.wikimedia.org/wikipedia/commons/b/b3/Oryzias_javanicus.jpg"
  ],
  "gallery": [],
  "tags": [
    "saumâtre",
    "carnivore",
    "nano",
    "facile"
  ]
}