{
  "name": "Gourami géant",
  "scientificName": "Osphronemus goramy",
  "slug": "osphronemus-goramy",
  "biotope": "Eau saumâtre",
  "difficulty": 1,
  "tempMin": 17,
  "tempMax": 27,
  "phMin": 6.5,
  "phMax": 8,
  "ghMin": 25,
  "ghMax": 25,
  "khMin": null,
  "khMax": null,
  "minVolumeL": null,
  "minLengthCm": 80,
  "behavior": "Adapté aux eaux saumâtres, souvent actif et robuste. Peut tolérer des variations de salinité.",
  "compatibility": "Compatible avec les espèces tolérant les mêmes conditions saumâtres.",
  "diet": "Omnivore vorace : granulés, fruits, légumes, poissons, vers de terre — mange de tout.",
  "breeding": "Ovipare, disperseur d'œufs dans la végétation ou la mousse.",
  "notes": "Bac planté avec espace de nage. Eau douce et légèrement acide.",
  "images": [
    "https://www.b-aqua.com/photos/1/2502.jpg"
  ],
  "gallery": [],
  "tags": [
    "saumâtre",
    "grand",
    "facile"
  ]
}