{
  "name": "Pomacanthus imperator",
  "scientificName": "Pomacanthus imperator",
  "slug": "pomacanthus-imperator",
  "biotope": "Eau de mer",
  "difficulty": 1,
  "tempMin": 22,
  "tempMax": 26,
  "phMin": 7,
  "phMax": 8.5,
  "ghMin": null,
  "ghMax": null,
  "khMin": null,
  "khMax": null,
  "minVolumeL": null,
  "minLengthCm": 35,
  "behavior": "Actif, nage parmi les coraux et roches du récif.",
  "compatibility": "Compatible avec les poissons récifaux de tempérament similaire.",
  "diet": "Omnivore marin : mysis, artémias, nourriture congelée marine, paillettes marines.",
  "breeding": "Ovipare. Reproduction rarement réalisée en captivité.",
  "notes": "Bac récifal avec paramètres stables. Qualité de l'eau excellente requise.",
  "images": [
    "https://upload.wikimedia.org/wikipedia/commons/thumb/2/29/Emperor_Angelfish%2C_Western_form_-_Pomacanthus_imperator_1.jpg/800px-Emperor_Angelfish%2C_Western_form_-_Pomacanthus_imperator_1.jpg"
  ],
  "gallery": [],
  "tags": [
    "marin",
    "grand",
    "facile"
  ]
}