{
  "name": "Pseudopimelodus mangurus",
  "scientificName": "Pseudopimelodus mangurus",
  "slug": "pseudopimelodus-mangurus",
  "biotope": "Eau douce — Amazonie",
  "difficulty": 1,
  "tempMin": 24,
  "tempMax": 28,
  "phMin": 6.5,
  "phMax": 7.5,
  "ghMin": null,
  "ghMax": null,
  "khMin": null,
  "khMax": null,
  "minVolumeL": null,
  "minLengthCm": 70,
  "behavior": "Zone: Fond",
  "compatibility": "Zone fond.",
  "diet": "Omnivore : granulés pour cichlidés, artémias, vers de vase, nourriture congelée.",
  "breeding": "Ovipare, pondeur sur substrat. Soins biparentaux dans la plupart des cas.",
  "notes": "Bac spacieux avec racines et cachettes. Substrat sableux.",
  "images": [
    "https://static.inaturalist.org/photos/63278897/medium.jpg"
  ],
  "gallery": [],
  "tags": [
    "eau-douce",
    "grand",
    "facile"
  ]
}