{
  "name": "Scalaire",
  "scientificName": "Pterophyllum scalare",
  "slug": "pterophyllum-scalare",
  "biotope": "Eau douce",
  "difficulty": 3,
  "tempMin": 24,
  "tempMax": 26,
  "phMin": 6.8,
  "phMax": 7.2,
  "ghMin": 5,
  "ghMax": 12,
  "khMin": 3,
  "khMax": 10,
  "minVolumeL": 300,
  "minLengthCm": 15,
  "behavior": "Comportement grégaire, peut devenir territorial.",
  "compatibility": "Avec poissons paisibles et non trop petits; éviter prédateurs.",
  "diet": "Carnivore/insectivore: granulés, congelés, proies vivantes.",
  "breeding": "Ovipare/ponte sur substrat; formage de couples.",
  "notes": "Préférer grandes hauteurs d'eau et bac planté; volume recommandé élevé.",
  "images": [
    "https://www.fishipedia.fr/wp-content/uploads/2019/01/Pterophyllum-scalare-2.jpg"
  ],
  "gallery": [],
  "tags": [
    "cichlidae",
    "angelfish",
    "mi-grande"
  ]
}