{
  "name": "Cascudo (port)",
  "scientificName": "Rineloricaria lanceolata",
  "slug": "rineloricaria-lanceolata",
  "biotope": "Eau douce",
  "difficulty": 1,
  "tempMin": 25,
  "tempMax": 26,
  "phMin": 6,
  "phMax": 8,
  "ghMin": 5,
  "ghMax": 19,
  "khMin": null,
  "khMax": null,
  "minVolumeL": null,
  "minLengthCm": 13,
  "behavior": "Zone: Inférieure",
  "compatibility": "Zone inférieure.",
  "diet": "Herbivore",
  "breeding": null,
  "notes": null,
  "images": [],
  "gallery": [],
  "tags": [
    "eau-douce",
    "facile"
  ]
}