{
  "name": "Rivulus cylindraceus",
  "scientificName": "Rivulus cylindraceus",
  "slug": "rivulus-cylindraceus",
  "biotope": "Eau douce",
  "difficulty": 1,
  "tempMin": 22,
  "tempMax": 28,
  "phMin": 7,
  "phMax": 7,
  "ghMin": 7,
  "ghMax": 9,
  "khMin": null,
  "khMax": null,
  "minVolumeL": null,
  "minLengthCm": 5.5,
  "behavior": "Zone: Supérieure",
  "compatibility": "Zone supérieure.",
  "diet": "Non renseigné",
  "breeding": "Ovipare",
  "notes": null,
  "images": [],
  "gallery": [],
  "tags": [
    "eau-douce",
    "facile"
  ]
}