{
  "name": "Gourami Clair de Lune",
  "scientificName": "Trichopodus microlepis",
  "slug": "trichopodus-microlepis",
  "biotope": "Eau douce",
  "difficulty": 2,
  "tempMin": 22,
  "tempMax": 32,
  "phMin": 6,
  "phMax": 7.5,
  "ghMin": 2,
  "ghMax": 25,
  "khMin": null,
  "khMax": null,
  "minVolumeL": 250,
  "minLengthCm": 15,
  "behavior": "Population: 4 minimum. Zone: Centrale, Supérieure. Ratio M/F: 1 / 3",
  "compatibility": "Zone centrale, supérieure.",
  "diet": "Carnivore",
  "breeding": "Ovipare, difficulté: Possible",
  "notes": "En cours de rédaction : Trichopodus microlepis est très commun dans la plaine inondable du bas Mékong et on peut donc supposer que la large plage de paramètres acceptables par l'espèce soit due aux importantes variations saisonnières de son milieu. ?? Ce poisson préfère toutefois une eau douce et acide, le pH sera compris entre 6,0 à 7,0 , une dureté de GH 2 à 15 et la température maintenue ent...",
  "images": [],
  "gallery": [],
  "tags": [
    "eau-douce",
    "carnivore"
  ]
}