{
  "name": "Valenciennea strigata",
  "scientificName": "Valenciennea strigata",
  "slug": "valenciennea-strigata",
  "biotope": "Eau de mer",
  "difficulty": 1,
  "tempMin": 26,
  "tempMax": 28,
  "phMin": 8,
  "phMax": 8,
  "ghMin": null,
  "ghMax": null,
  "khMin": null,
  "khMax": null,
  "minVolumeL": null,
  "minLengthCm": 18,
  "behavior": "Population: 2 minimum.",
  "compatibility": "Compatible avec les poissons récifaux de tempérament similaire.",
  "diet": "Carnivore benthique : tamise le sable pour trouver micro-crustacés, mysis, artémias.",
  "breeding": "Ovipare. Le couple pond dans un terrier. Le mâle peut incuber en bouche.",
  "notes": "Bac récifal avec paramètres stables. Qualité de l'eau excellente requise.",
  "images": [
    "https://www.b-aqua.com/photos/1/3390.jpg"
  ],
  "gallery": [],
  "tags": [
    "marin",
    "carnivore",
    "facile"
  ]
}